aerodynamics/__init__.py
aerodynamics/aero.py
aerodynamics-0.0.1.dev1.dist-info/LICENSE
aerodynamics-0.0.1.dev1.dist-info/METADATA
aerodynamics-0.0.1.dev1.dist-info/WHEEL
aerodynamics-0.0.1.dev1.dist-info/top_level.txt
aerodynamics-0.0.1.dev1.dist-info/RECORD
